quant_opts-0.1.0.dist-info/METADATA
quant_opts-0.1.0.dist-info/WHEEL
quant_opts/__init__.py
quant_opts/__init__.pyi
quant_opts/__pycache__/__init__.cpython-312.pyc
quant_opts/core.abi3.so
quant_opts/core.pyi
quant_opts/py.typed
quant_opts-0.1.0.dist-info/RECORD
