Metadata-Version: 2.4
Name: quant-opts
Version: 0.1.0
Classifier: Programming Language :: Rust
Classifier: Programming Language :: Python
Classifier: Programming Language :: Python :: 3
Classifier: Programming Language :: Python :: 3 :: Only
Classifier: License :: OSI Approved :: MIT License
Requires-Dist: maturin ; extra == 'dev'
Provides-Extra: dev
Summary: Python bindings for quant-opts
Author: Prem Olszewski, Hayden Rose
License: MIT
Requires-Python: >=3.9
